maniac/__init__.py
maniac/async_client.py
maniac/client.py
maniac/containers.py
maniac/loop_runner.py
maniac/old_client.py
maniac/token_manager.py
maniac/token_manager_async.py
maniac/transport.py
maniac/types.py
maniac/evals/register_eval_artifact.py
maniac/transports/httpx_sync.py
maniac/utils/http_utils.py
maniac/utils/inference_utils.py
maniac-0.3.7.dist-info/licenses/LICENSE
maniac-0.3.7.dist-info/METADATA
maniac-0.3.7.dist-info/WHEEL
maniac-0.3.7.dist-info/top_level.txt
maniac-0.3.7.dist-info/RECORD
