Metadata-Version: 2.4
Name: maniac
Version: 0.3.7
Summary: LLM inference SDK, for telemetry and internal model routing
Author-email: Roshan Prabhakar <roshan@maniaclabs.xyz>, Tom Shahar <tom.e.shahar@gmail.com>
License:                     GNU GENERAL PUBLIC LICENSE
Project-URL: Homepage, https://www.maniac.ai/
Classifier: Programming Language :: Python :: 3
Classifier: Operating System :: OS Independent
Requires-Python: >=3.9
License-File: LICENSE
Requires-Dist: aiohttp<4,>=3.9
Requires-Dist: certifi
Requires-Dist: httpx[http2]
Provides-Extra: evals
Requires-Dist: cloudpickle; extra == "evals"
Dynamic: license-file
